omero/analysis_scripts/Kymograph.py
omero/analysis_scripts/Kymograph_Analysis.py
omero/analysis_scripts/Plot_Profile.py
omero/analysis_scripts/__init__.py
omero/annotation_scripts/Convert_KeyVal_namespace.py
omero/annotation_scripts/Export_to_csv.py
omero/annotation_scripts/Import_from_csv.py
omero/annotation_scripts/Remove_KeyVal.py
omero/annotation_scripts/__init__.py
omero/export_scripts/Batch_Image_Export.py
omero/export_scripts/Batch_ROI_Export.py
omero/export_scripts/Make_Movie.py
omero/export_scripts/__init__.py
omero/figure_scripts/Movie_Figure.py
omero/figure_scripts/Movie_ROI_Figure.py
omero/figure_scripts/ROI_Split_Figure.py
omero/figure_scripts/Split_View_Figure.py
omero/figure_scripts/Thumbnail_Figure.py
omero/figure_scripts/__init__.py
omero/import_scripts/Populate_Metadata.py
omero/import_scripts/Populate_ROI.py
omero/import_scripts/__init__.py
omero/util_scripts/Channel_Offsets.py
omero/util_scripts/Combine_Images.py
omero/util_scripts/Dataset_To_Plate.py
omero/util_scripts/Images_From_ROIs.py
omero/util_scripts/Move_Annotations.py
omero/util_scripts/__init__.py
omero_scripts-5.9.1.dist-info/METADATA
omero_scripts-5.9.1.dist-info/WHEEL
omero_scripts-5.9.1.dist-info/top_level.txt
omero_scripts-5.9.1.dist-info/RECORD
