Metadata-Version: 2.4
Name: omero-scripts
Version: 5.9.1
Summary: OMERO scripts
Home-page: https://github.com/ome/omero-scripts/
Download-URL: https://github.com/ome/omero-scripts/
Author: The Open Microscopy Team
Author-email: ome-devel@lists.openmicroscopy.org.uk
License: GPL-2.0+
Classifier: Development Status :: 5 - Production/Stable
Classifier: Environment :: Plugins
Classifier: Intended Audience :: Developers
Classifier: Intended Audience :: End Users/Desktop
Classifier: Intended Audience :: Science/Research
Classifier: License :: OSI Approved :: GNU General Public License v2 or later (GPLv2+)
Classifier: Natural Language :: English
Classifier: Operating System :: OS Independent
Classifier: Programming Language :: Python :: 3
Classifier: Topic :: Software Development :: Libraries :: Python Modules
Requires-Python: >=3
Dynamic: author
Dynamic: author-email
Dynamic: classifier
Dynamic: description
Dynamic: download-url
Dynamic: home-page
Dynamic: license
Dynamic: requires-python
Dynamic: summary
